MSIGen/__init__.py
MSIGen/base_class.py
MSIGen/D.py
MSIGen/GUI.py
MSIGen/msigen.py
MSIGen/mzml.py
MSIGen/raw.py
MSIGen/timsdata.dll
MSIGen/tsf.py
MSIGen/visualization.py
msigen-0.3.1.dist-info/entry_points.txt
msigen-0.3.1.dist-info/LICENSE.txt
msigen-0.3.1.dist-info/METADATA
msigen-0.3.1.dist-info/WHEEL
msigen-0.3.1.dist-info/RECORD
