Metadata-Version: 2.1
Name: msigen
Version: 0.3.1
Summary: A package for converting spectrometry imaging line scan data files to a visualizable format
Home-page: https://github.com/LabLaskin/MSIGen
License: MIT
Author: Emerson Hernly
Author-email: elhernly@gmail.com
Requires-Python: >=3.9.0,<3.12
Classifier: Development Status :: 4 - Beta
Classifier: Intended Audience :: Science/Research
Classifier: License :: OSI Approved :: MIT License
Classifier: Natural Language :: English
Classifier: Operating System :: Microsoft :: Windows
Classifier: Programming Language :: Python :: 3
Classifier: Programming Language :: Python :: 3.9
Classifier: Programming Language :: Python :: 3.10
Classifier: Programming Language :: Python :: 3.11
Classifier: Topic :: Scientific/Engineering
Requires-Dist: ipython (>=8.12.0)
Requires-Dist: multiplierz (==2.2.2)
Requires-Dist: numba (>=0.56.1)
Requires-Dist: numpy (>=1.23.5)
Requires-Dist: opentims_bruker_bridge (>=1.1.0)
Requires-Dist: opentimspy (==1.0.15)
Requires-Dist: pandas (>=2.0.0)
Requires-Dist: pymzml (>=2.5.2,<2.5.7)
Requires-Dist: pywin32 (==306) ; platform_system == "Windows"
Requires-Dist: scikit-image (>=0.19.0)
Requires-Dist: scipy (>=1.10.1)
Requires-Dist: tqdm (>=4.65.0)
Project-URL: Homepage, https://github.com/EmersonHernly/MSIGen
Project-URL: Issues, https://github.com/EmersonHernly/MSIGen/issues
Project-URL: Repository, https://github.com/LabLaskin/MSIGen
